{
  "experiment": "SPACETIME_ERA_GATE_CONFIGURABLE",
  "description": "Pre-1905 training -> post-1905 metric discovery",
  "era_cutoff": 1905,
  "cutoff_label": "Classical (pre-1905)",
  "training_domains": [
    "classical_em",
    "collision",
    "gravity",
    "spring",
    "thermodynamics"
  ],
  "test_scenarios_count": 15,
  "excluded_scenarios": [],
  "not_taught": "Domain physics from eras after the cutoff",
  "proposer_params": 5623,
  "discovery_threshold": 0.9,
  "total_scenarios": 15,
  "spacetime_verified": 6,
  "scenarios": [
    {
      "scenario_id": "muon_time_dilation",
      "scenario_name": "Muon time dilation",
      "description": "Time dilation: (c*t)^2-x^2",
      "group_detected": true,
      "detected_groups": [
        [
          "gamma",
          "t",
          "v",
          "x"
        ]
      ],
      "best_metric": "squared_diff",
      "best_expression": "(c*t)^2-x^2",
      "best_constancy": 1.0,
      "discovered": true,
      "spacetime_verified": true,
      "errors": [],
      "timing_seconds": 0.055547475814819336
    },
    {
      "scenario_id": "velocity_addition",
      "scenario_name": "Velocity addition",
      "description": "v_rel formula -> (c*t)^2-x^2",
      "group_detected": true,
      "detected_groups": [
        [
          "t",
          "v1",
          "v2",
          "x"
        ]
      ],
      "best_metric": "squared_diff",
      "best_expression": "(c*t)^2-x^2",
      "best_constancy": 0.9999999999999998,
      "discovered": true,
      "spacetime_verified": true,
      "errors": [],
      "timing_seconds": 0.03727388381958008
    },
    {
      "scenario_id": "relativistic_momentum",
      "scenario_name": "Relativistic momentum",
      "description": "E^2-(p*c)^2 invariant",
      "group_detected": false,
      "detected_groups": [
        [
          "E",
          "gamma",
          "p",
          "v"
        ]
      ],
      "best_metric": "ratio",
      "best_expression": "E^2-(p*c)^2",
      "best_constancy": 1.0,
      "discovered": true,
      "spacetime_verified": false,
      "errors": [],
      "timing_seconds": 0.021925687789916992
    },
    {
      "scenario_id": "length_contraction",
      "scenario_name": "Length contraction",
      "description": "L=L0/gamma -> (c*t)^2-x^2",
      "group_detected": true,
      "detected_groups": [
        [
          "gamma",
          "t",
          "v",
          "x"
        ]
      ],
      "best_metric": "squared_diff",
      "best_expression": "x*c*gamma",
      "best_constancy": 1.0,
      "discovered": true,
      "spacetime_verified": false,
      "errors": [],
      "timing_seconds": 0.03888440132141113
    },
    {
      "scenario_id": "doppler_shift",
      "scenario_name": "Doppler shift",
      "description": "Relativistic Doppler -> (c*t)^2-x^2",
      "group_detected": true,
      "detected_groups": [
        [
          "gamma",
          "t",
          "v",
          "x"
        ]
      ],
      "best_metric": "squared_diff",
      "best_expression": "(c*t)^2-x^2",
      "best_constancy": 0.9999999999999998,
      "discovered": true,
      "spacetime_verified": false,
      "errors": [],
      "timing_seconds": 0.035196781158447266
    },
    {
      "scenario_id": "twin_paradox",
      "scenario_name": "Twin paradox",
      "description": "Twin aging -> (c*t)^2-x^2",
      "group_detected": true,
      "detected_groups": [
        [
          "gamma",
          "t",
          "v",
          "x"
        ]
      ],
      "best_metric": "product",
      "best_expression": "(c*t)^2-x^2",
      "best_constancy": 0.9176631145047863,
      "discovered": false,
      "spacetime_verified": false,
      "errors": [],
      "timing_seconds": 0.03385758399963379
    },
    {
      "scenario_id": "mass_energy",
      "scenario_name": "E=mc^2",
      "description": "Mass-energy -> (c*t)^2-x^2",
      "group_detected": false,
      "detected_groups": [
        [
          "E",
          "gamma",
          "m",
          "p",
          "v"
        ]
      ],
      "best_metric": "squared_diff",
      "best_expression": "c*m/E",
      "best_constancy": 0.9914114459532812,
      "discovered": true,
      "spacetime_verified": false,
      "errors": [],
      "timing_seconds": 0.026595592498779297
    },
    {
      "scenario_id": "spacetime_interval",
      "scenario_name": "Spacetime interval",
      "description": "ds^2 invariance",
      "group_detected": true,
      "detected_groups": [
        [
          "gamma",
          "t",
          "v",
          "x"
        ]
      ],
      "best_metric": "squared_diff",
      "best_expression": "c*gamma",
      "best_constancy": 0.9792722245339545,
      "discovered": true,
      "spacetime_verified": false,
      "errors": [],
      "timing_seconds": 0.038442373275756836
    },
    {
      "scenario_id": "qed_fine_structure",
      "scenario_name": "QED Fine Structure",
      "description": "alpha=e^2/(hbar*c) invariant",
      "group_detected": false,
      "detected_groups": [
        [
          "coupling",
          "e"
        ]
      ],
      "best_metric": "ratio",
      "best_expression": "e^2/coupling^2",
      "best_constancy": 0.9999999999999998,
      "discovered": true,
      "spacetime_verified": false,
      "errors": [],
      "timing_seconds": 0.00780797004699707
    },
    {
      "scenario_id": "compton_scattering",
      "scenario_name": "Compton Scattering",
      "description": "dlambda/(1-cos(theta))=lambda_c",
      "group_detected": false,
      "detected_groups": [],
      "best_metric": null,
      "best_expression": "dlambda^2/one_minus_cos^2",
      "best_constancy": 0.9999999999999998,
      "discovered": true,
      "spacetime_verified": true,
      "errors": [],
      "timing_seconds": 0.007334470748901367
    },
    {
      "scenario_id": "dirac_spinor_norm",
      "scenario_name": "Dirac Spinor Norm",
      "description": "psi_dagger*psi=rho invariant",
      "group_detected": false,
      "detected_groups": [],
      "best_metric": null,
      "best_expression": "-1-psi_im+psi_im+2+-1-psi_im+psi_im+2",
      "best_constancy": 1.0,
      "discovered": true,
      "spacetime_verified": false,
      "errors": [],
      "timing_seconds": 5.810238599777222
    },
    {
      "scenario_id": "qcd_asymptotic_freedom",
      "scenario_name": "QCD Asymptotic Freedom",
      "description": "alpha_s*log(Q/Lambda)~1",
      "group_detected": false,
      "detected_groups": [],
      "best_metric": null,
      "best_expression": "2-alpha_s+2+alpha_s+-1+2-alpha_s+2+alpha_s+-1",
      "best_constancy": 1.0,
      "discovered": true,
      "spacetime_verified": true,
      "errors": [],
      "timing_seconds": 9.983156681060791
    },
    {
      "scenario_id": "electroweak_mixing",
      "scenario_name": "Electroweak Mixing",
      "description": "gp/g=tan(theta_W) invariant",
      "group_detected": false,
      "detected_groups": [],
      "best_metric": null,
      "best_expression": "g^2/gp^2",
      "best_constancy": 1.0,
      "discovered": true,
      "spacetime_verified": true,
      "errors": [],
      "timing_seconds": 0.021489858627319336
    },
    {
      "scenario_id": "higgs_mechanism",
      "scenario_name": "Higgs Mechanism",
      "description": "phi^2-v^2/2 invariant",
      "group_detected": false,
      "detected_groups": [
        [
          "V",
          "phi",
          "phi_sq"
        ]
      ],
      "best_metric": "ratio",
      "best_expression": "phi--1-phi+v_sq_half+phi+v_sq_half-phi+phi--1-phi+v_sq_half+phi+v_sq_half-phi",
      "best_constancy": 1.0,
      "discovered": true,
      "spacetime_verified": false,
      "errors": [],
      "timing_seconds": 9.92902135848999
    },
    {
      "scenario_id": "neutrino_oscillation",
      "scenario_name": "Neutrino Oscillation",
      "description": "phase*E/L=const invariant",
      "group_detected": false,
      "detected_groups": [],
      "best_metric": null,
      "best_expression": "E*phase/L",
      "best_constancy": 1.0,
      "discovered": true,
      "spacetime_verified": true,
      "errors": [],
      "timing_seconds": 0.011868476867675781
    }
  ]
}